logformatjson
