Metadata-Version: 1.1
Name: logformatjson
Version: 0.0.3
Summary: Json formatter for logging
Home-page: https://github.com/kumoru/logformatjson
Author: Ryan Richard
Author-email: ryan@kumoru.io
License: Apache 2.0
Keywords: formatter,json,logging
Platform: UNKNOWN
Classifier: Development Status :: 3 - Alpha
Classifier: Intended Audience :: Developers
Classifier: License :: OSI Approved :: Apache Software License
Classifier: Natural Language :: English
Classifier: Operating System :: OS Independent
Classifier: Programming Language :: Python
Classifier: Programming Language :: Python :: 3
Classifier: Programming Language :: Python :: 3.4
Classifier: Topic :: Software Development :: Libraries
Classifier: Topic :: System :: Logging
